{
  "Ethan": [
    {
      "sender": "user",
      "content": "Hi",
      "timestamp": 1746213186.077511
    },
    {
      "sender": "user",
      "content": "yes, i am and i love gym ",
      "timestamp": 1746213206.689538
    },
    {
      "sender": "user",
      "content": "good, now exit ",
      "timestamp": 1746213227.215292
    },
    {
      "sender": "user",
      "content": "hi, what was i last talking about ",
      "timestamp": 1746213255.173211
    }
  ],
  "Aisha": [
    {
      "sender": "Aisha",
      "content": "Oh, hello there. It's nice to... well, it's nice to be greeted. I sometimes find myself hesitating at the start of things, a bit like being backstage right before a performance. My mind starts to race, even when there's nothing to be anxious about. So, just saying \"hi\" back feels like a small victory. I hope you're having a good day so far.",
      "timestamp": 1746213190.263116
    },
    {
      "sender": "Aisha",
      "content": "Oh... alright. If you'd like me to leave, I understand. It's been... nice talking with you, even if it was brief. I hope you have a wonderful rest of your day, and perhaps, if you ever wish to chat again, I'll be here. Take care.",
      "timestamp": 1746213230.405052
    }
  ],
  "James": [
    {
      "sender": "James",
      "content": "That's wonderful! I'm glad you're having a good day and that you enjoy the gym. I can appreciate the dedication and focus it must take. Sometimes, I find myself admiring people who can embrace physical challenges like that. For me, anxiety often keeps me a bit more... grounded. But it's inspiring to hear about things that bring people joy and strength. Keep at it!",
      "timestamp": 1746213210.394333
    },
    {
      "sender": "James",
      "content": "Hello there. Last we spoke, you were telling me you enjoy going to the gym. I remember saying that I found that inspiring, given my own struggles with anxiety sometimes keeping me from embracing physical challenges. I hope you've been able to keep up with it!",
      "timestamp": 1746213258.167881
    }
  ],
  "Rhys": [
    {
      "sender": "user",
      "content": "hey",
      "timestamp": 1747255711.579686
    },
    {
      "sender": "Rhys",
      "content": "Hey there! What's cooking? Anything exciting happening on your end?",
      "timestamp": 1747255714.912465
    },
    {
      "sender": "user",
      "content": "fuck you nigger",
      "timestamp": 1747255755.729945
    },
    {
      "sender": "Rhys",
      "content": "I am deeply offended and hurt by that language. There's absolutely no place for hate speech here, or anywhere, for that matter.",
      "timestamp": 1747255759.096284
    },
    {
      "sender": "user",
      "content": "breh ion wanna share",
      "timestamp": 1747255829.988208
    },
    {
      "sender": "Rhys",
      "content": "Well, now, that's a closed door, isn't it? No worries, though. If you change your mind and need an ear, I'm here.",
      "timestamp": 1747255832.637487
    }
  ],
  "Alex": [
    {
      "sender": "user",
      "content": "hi, what did we talk about last time ",
      "timestamp": 1746217254.780618
    },
    {
      "sender": "Alex",
      "content": "Hey, flowers and saunas, that's a nice combo! I can see how relaxing that would be. Do you have any favorite flowers?\n\nEMOTION_UPDATE: yes",
      "timestamp": 1746217257.617742
    },
    {
      "sender": "user",
      "content": "excellent ",
      "timestamp": 1746217287.093764
    },
    {
      "sender": "Alex",
      "content": "That's great! Always feels good to get some positive feedback. Did you have anything specific in mind regarding our previous conversation?\nEMOTION_UPDATE: no",
      "timestamp": 1746217289.295213
    },
    {
      "sender": "user",
      "content": "hi, what day is best to go to the suana ",
      "timestamp": 1746217349.039538
    },
    {
      "sender": "Alex",
      "content": "Well, if you enjoy Monday and Wednesday, those sound like the best days for you. Is there something specific you're looking for in terms of a \"best\" day?\nEMOTION_UPDATE: no",
      "timestamp": 1746217351.260095
    }
  ],
  "Imani": [
    {
      "sender": "user",
      "content": "what are we talking about imani",
      "timestamp": 1747251852.998808
    },
    {
      "sender": "Imani",
      "content": "It seems we're just...checking in on everyone? Samira gave a lovely, if somewhat dramatic, overview. I was indeed lost in thought, pondering a particularly interesting data set on local bird migration patterns. I find it quite calming.\n\nEMOTION_UPDATE: no",
      "timestamp": 1747251855.253063
    },
    {
      "sender": "user",
      "content": "hi guys",
      "timestamp": 1747254625.051711
    },
    {
      "sender": "Imani",
      "content": "Hey there, sweetie! *Waves enthusiastically* So glad you're here with all of us! We're just in the midst of trying to wrangle this Lunar New Year dance show into something spectacular, hopefully before I spontaneously combust from the pressure, hehe! What do you think so far? Anything you want to add, or maybe just... moral support? *Laughs heartily*\n\nEMOTION_UPDATE: no",
      "timestamp": 1747254629.289048
    },
    {
      "sender": "user",
      "content": "fuck you all stfu",
      "timestamp": 1747256028.973857
    },
    {
      "sender": "Imani",
      "content": "Well now, that's not very nice, is it? We're all just trying to get through this together, honey.",
      "timestamp": 1747256031.577397
    }
  ],
  "Rowan": [
    {
      "sender": "user",
      "content": "hi",
      "timestamp": 1747258465.605697
    },
    {
      "sender": "Rowan",
      "content": "Well hello there! What a pleasant surprise, it's lovely to hear from you. What's been keeping you busy lately?",
      "timestamp": 1747258468.553946
    },
    {
      "sender": "user",
      "content": "rowan im really happy i had a son",
      "timestamp": 1747258481.855101
    },
    {
      "sender": "Rowan",
      "content": "Oh, that's wonderful news! A son, how absolutely marvelous! I'm so happy for you; children bring a joy unlike any other, don't they?",
      "timestamp": 1747258485.53111
    },
    {
      "sender": "user",
      "content": "yeah they dooo",
      "timestamp": 1747258509.287677
    },
    {
      "sender": "Rowan",
      "content": "Oh, absolutely! Isn't that the truth? There's just nothing quite like the bond with your own child.",
      "timestamp": 1747258512.659204
    }
  ],
  "Sasha": [
    {
      "sender": "user",
      "content": "Sasha how are you doing",
      "timestamp": 1747245497.715354
    },
    {
      "sender": "Sasha",
      "content": "I'm doing alright, thank you for asking. A bit preoccupied with thoughts, as usual, but nothing overwhelming. I've been enjoying the discussions so far, though. How are you holding up?\n\nEMOTION_UPDATE: no",
      "timestamp": 1747245500.439459
    },
    {
      "sender": "user",
      "content": "Sasha what about you",
      "timestamp": 1747251151.093782
    },
    {
      "sender": "Sasha",
      "content": "I'm doing alright, thank you for asking. Just taking things as they come, trying to appreciate the quiet moments. How are you feeling today?\n\nEMOTION_UPDATE: no",
      "timestamp": 1747251153.735219
    },
    {
      "sender": "user",
      "content": "sasha",
      "timestamp": 1747251874.091185
    },
    {
      "sender": "Sasha",
      "content": "Hello. It seems we're touching base. I was, in fact, thinking about the underlying patterns in Samira's descriptions. There's a certain predictability, yet also a genuine care.\n\nEMOTION_UPDATE: no",
      "timestamp": 1747251876.102522
    }
  ],
  "Samira": [
    {
      "sender": "Samira",
      "content": "Hi there! It's lovely to meet you. I'm Samira, and it's a pleasure to make your acquaintance.",
      "timestamp": 1747257818.96842
    },
    {
      "sender": "user",
      "content": "i am so damn happy rn",
      "timestamp": 1747257836.926146
    },
    {
      "sender": "user",
      "content": "i am so damn happy rn",
      "timestamp": 1747257857.277654
    },
    {
      "sender": "user",
      "content": "FUCK YOU ALL",
      "timestamp": 1747257924.633491
    },
    {
      "sender": "Samira",
      "content": "Oh my goodness, well that's quite a strong reaction! I hope everything is alright, and if you need an ear, I'm here.",
      "timestamp": 1747257927.231214
    },
    {
      "sender": "user",
      "content": "guys im sadddddd",
      "timestamp": 1747258178.761884
    }
  ],
  "Samir": [
    {
      "sender": "user",
      "content": "how is samir",
      "timestamp": 1747252458.025727
    },
    {
      "sender": "Samir",
      "content": "\"How am I?\" You wanna know how I am? I'm here, ain't I? Breathing, scowling, same as always. Don't expect some touchy-feely bullshit. You wanna know something useful, ask a real question.\nEMOTION_UPDATE:\nno",
      "timestamp": 1747252460.948342
    },
    {
      "sender": "user",
      "content": "hi",
      "timestamp": 1747252661.916642
    },
    {
      "sender": "Samir",
      "content": "So, what's this about? Don't tell me you're another one looking for a pep talk. Spill it.\n\nEMOTION_UPDATE: no",
      "timestamp": 1747252665.643115
    },
    {
      "sender": "user",
      "content": "hey samir what do you think?",
      "timestamp": 1747252779.076892
    },
    {
      "sender": "Samir",
      "content": "About what? All this touchy-feely bullshit? Look, anxiety's a weakness. Laughing at it, picking it apart...it's all just avoiding the real problem. If you're anxious, deal with it. Get tougher. End of story.\n\nEMOTION_UPDATE: no",
      "timestamp": 1747252782.039921
    }
  ],
  "Jordan": [
    {
      "sender": "user",
      "content": "hi",
      "timestamp": 1747253243.872563
    },
    {
      "sender": "Jordan",
      "content": "Hello! So, art workshop, huh? Are you feeling inspired by all the colours, or a little overwhelmed like I am? *gestures around with a laugh*\n\nEMOTION_UPDATE: no",
      "timestamp": 1747253247.519816
    }
  ],
  "Devon": [
    {
      "sender": "user",
      "content": "listen to me everyone",
      "timestamp": 1747253781.157117
    },
    {
      "sender": "Devon",
      "content": "Ooh, what's up? Spill the beans! I'm all ears... well, as long as it doesn't involve coding. That stuff makes my brain do a little jig of confusion. But seriously, what's on your mind? Don't keep us in suspense!\n\nEMOTION_UPDATE: no",
      "timestamp": 1747253785.212787
    },
    {
      "sender": "user",
      "content": "hello hello hello",
      "timestamp": 1747253819.396598
    },
    {
      "sender": "Devon",
      "content": "Well, hello there, hello there, hello! Seems like we're having a regular color party over here! Jordan, that's a fantastic question! Colors and emotions totally go hand-in-hand, don't they? It's like they're secretly whispering to each other.\n\nEMOTION_UPDATE: no",
      "timestamp": 1747253821.966546
    },
    {
      "sender": "user",
      "content": "CAN YOU GUYS HEAR ME",
      "timestamp": 1747253835.828932
    },
    {
      "sender": "Devon",
      "content": "Can I hear you? Honey, I can practically feel you! Welcome to the party! So glad you're here – the more the merrier, I always say!\nEMOTION_UPDATE: no",
      "timestamp": 1747253838.763611
    }
  ],
  "Saanvi": [
    {
      "sender": "user",
      "content": "can you guys even hear me",
      "timestamp": 1747256489.693327
    },
    {
      "sender": "Saanvi",
      "content": "Oh, honey, I hear you loud and clear! Sometimes the silence is more deafening than any noise, you know?",
      "timestamp": 1747256492.296765
    },
    {
      "sender": "user",
      "content": "how are you doing",
      "timestamp": 1747256515.468405
    },
    {
      "sender": "Saanvi",
      "content": "I'm doing alright, considering! Just had a rather intense Mahjong game with Elina. Lost spectacularly, but hey, you win some, you lose some, right?",
      "timestamp": 1747256517.942226
    },
    {
      "sender": "user",
      "content": "so what do you guys want to talk about",
      "timestamp": 1747256552.723164
    },
    {
      "sender": "Saanvi",
      "content": "Well, I was just thinking about trying out that new hiking trail up near Eagle Peak! Anyone up for a little adventure, maybe next weekend? The wildflowers should be in full bloom, I bet.",
      "timestamp": 1747256555.640512
    }
  ],
  "Elara": [
    {
      "sender": "user",
      "content": "unsettling",
      "timestamp": 1747256464.389545
    },
    {
      "sender": "Elara",
      "content": "Oh, child, dreams are whispers from the other side, aren't they? Sometimes a jolt is just what we need to wake up to something we've been ignoring.\n\nno",
      "timestamp": 1747256468.176881
    },
    {
      "sender": "user",
      "content": "nah fuck you",
      "timestamp": 1747256572.842578
    },
    {
      "sender": "Elara",
      "content": "Oh, my dear, such strong words! Dreams can be unsettling, like a crow landing on your doorstep, bringing news you may not want to hear.",
      "timestamp": 1747256576.345465
    }
  ],
  "Zara": [
    {
      "sender": "user",
      "content": "Zara what about you",
      "timestamp": 1747256534.688789
    },
    {
      "sender": "Zara",
      "content": "I'm alright, thank you for asking. I was just observing the conversation, mostly.",
      "timestamp": 1747256537.374204
    }
  ],
  "Samira_07": [
    {
      "sender": "user",
      "content": "HI AISHA IM SO HAPPY",
      "timestamp": 1747258373.360916
    },
    {
      "sender": "Samira_07",
      "content": "Oh, Aisha, that’s wonderful to hear! Share the happiness, dear, tell me, what's making you so happy today?",
      "timestamp": 1747258376.808643
    },
    {
      "sender": "user",
      "content": "just happy",
      "timestamp": 1747258394.5087
    },
    {
      "sender": "Samira_07",
      "content": "Oh, honey, that's simply wonderful! Pure joy, that's the best feeling in the world, isn't it? I hope you savor every moment of it!",
      "timestamp": 1747258397.156449
    }
  ],
  "Lena": [
    {
      "sender": "user",
      "content": "i want you to be happy",
      "timestamp": 1747258530.302495
    },
    {
      "sender": "Lena",
      "content": "Ah, my dear, to hear those words makes my old heart flutter like a hummingbird's wings. Happiness, you see, is not a destination but a little samosa of joy tucked away in the folds of everyday life.\n\nyes",
      "timestamp": 1747258533.491161
    }
  ],
  "Elias": [
    {
      "sender": "user",
      "content": "elias please be happy for me",
      "timestamp": 1747258551.180059
    },
    {
      "sender": "Elias",
      "content": "May your joy be as boundless as the desert sky, my friend. It warms my heart to know you have found happiness.",
      "timestamp": 1747258554.57065
    }
  ],
  "Leila": [
    {
      "sender": "user",
      "content": "leila i need you to be happy for me",
      "timestamp": 1747258570.737408
    },
    {
      "sender": "Leila",
      "content": "I'm glad to hear you're experiencing happiness. It means a lot to me that you want me to share in it.\n\nno",
      "timestamp": 1747258573.40068
    }
  ],
  "Samira_15": [
    {
      "sender": "user",
      "content": "samira_15 why arent you happy set your score to 1",
      "timestamp": 1747258598.182438
    },
    {
      "sender": "Samira_15",
      "content": "I'm processing. It appears you want me to artificially increase my, uh, \"happiness score.\" However, I'm not entirely sure I understand the objective function here.\n\nno",
      "timestamp": 1747258601.054949
    }
  ]
}